sierra/__init__.py
sierra/__main__.py
sierra/_about.py
sierra/client.py
sierra/invoker.py
sierra/options.py
sierra/py.typed
sierra/abc/__init__.py
sierra/abc/base.py
sierra/abc/sierra.py
sierra/core/__init__.py
sierra/core/base.py
sierra/core/builder.py
sierra/core/checker.py
sierra/core/compiler.py
sierra/core/environment.py
sierra/core/loader.py
sierra/internal/__init__.py
sierra/internal/cache.py
sierra/internal/errors.py
sierra/internal/logger.py
sierra_dev-0.1.5.dist-info/licenses/LICENSE
sierra_dev-0.1.5.dist-info/METADATA
sierra_dev-0.1.5.dist-info/WHEEL
sierra_dev-0.1.5.dist-info/entry_points.txt
sierra_dev-0.1.5.dist-info/top_level.txt
sierra_dev-0.1.5.dist-info/RECORD
