Metadata-Version: 2.4
Name: sierra-dev
Version: 0.1.5
Summary: A framework for building and managing invoker scripts across different nodes in Sierra.
Home-page: https://github.com/xsyncio/sierra-dev
Author: Xsyncio
Project-URL: Documentation, https://xsyncio.github.io/sierra-dev
Project-URL: Source, https://github.com/xsyncio/sierra-dev
Project-URL: Tracker, https://github.com/xsyncio/sierra-dev/issues
Keywords: sierra,invoker,script,framework
Classifier: Development Status :: 3 - Alpha
Classifier: Intended Audience :: Developers
Classifier: Topic :: Software Development :: Libraries :: Application Frameworks
Classifier: License :: OSI Approved :: GNU Affero General Public License v3
Classifier: Programming Language :: Python :: 3.12
Classifier: Operating System :: OS Independent
Requires-Python: >=3.12
License-File: LICENSE
Requires-Dist: colorama==0.4.6
Requires-Dist: httpx==0.28.1
Provides-Extra: dev
Requires-Dist: setuptools==80.9.0; extra == "dev"
Requires-Dist: ruff==0.12.4; extra == "dev"
Provides-Extra: docs
Requires-Dist: mkdocs==1.6.1; extra == "docs"
Requires-Dist: mkdocs-autorefs==1.4.2; extra == "docs"
Requires-Dist: mkdocs-dracula-theme==1.0.7; extra == "docs"
Requires-Dist: mkdocs-get-deps==0.2.0; extra == "docs"
Requires-Dist: mkdocs-git-committers-plugin-2==2.5.0; extra == "docs"
Requires-Dist: mkdocs-git-revision-date-localized-plugin==1.4.7; extra == "docs"
Requires-Dist: mkdocs-glightbox==0.4.0; extra == "docs"
Requires-Dist: mkdocs-llmstxt==0.3.0; extra == "docs"
Requires-Dist: mkdocs-material==9.6.15; extra == "docs"
Requires-Dist: mkdocs-material-extensions==1.3.1; extra == "docs"
Requires-Dist: mkdocs-minify-plugin==0.8.0; extra == "docs"
Requires-Dist: mkdocs-print-site-plugin==2.7.3; extra == "docs"
Requires-Dist: mkdocs-social-plugin==0.1.0; extra == "docs"
Requires-Dist: mkdocs-with-pdf==0.9.3; extra == "docs"
Requires-Dist: mkdocstrings==0.29.1; extra == "docs"
Requires-Dist: mkdocstrings-python==1.16.12; extra == "docs"
Requires-Dist: pymdown-extensions==10.16; extra == "docs"
Requires-Dist: Markdown==3.8.2; extra == "docs"
Requires-Dist: markdown-it-py==3.0.0; extra == "docs"
Requires-Dist: markdownify==1.1.0; extra == "docs"
Requires-Dist: jupyterlab_pygments==0.3.0; extra == "docs"
Requires-Dist: Pygments==2.19.2; extra == "docs"
Dynamic: author
Dynamic: classifier
Dynamic: description
Dynamic: description-content-type
Dynamic: home-page
Dynamic: keywords
Dynamic: license-file
Dynamic: project-url
Dynamic: provides-extra
Dynamic: requires-dist
Dynamic: requires-python
Dynamic: summary
